mydataviewer/___init__.py
mydataviewer/data_import_dialog.py
mydataviewer/data_viewer.py
mydataviewer/dataframe_model.py
mydataviewer/observable_dataframe.py
mydataviewer/themes.py
mydataviewer/view_dataframe.py
mydataviewer/assets/icon.ico
mydataviewer/docs/images/image_light.png
mydataviewer/docs/images/image_solarized.png
mydataviewer_GUI-0.2.dist-info/LICENSE.txt
mydataviewer_GUI-0.2.dist-info/METADATA
mydataviewer_GUI-0.2.dist-info/WHEEL
mydataviewer_GUI-0.2.dist-info/entry_points.txt
mydataviewer_GUI-0.2.dist-info/top_level.txt
mydataviewer_GUI-0.2.dist-info/RECORD
