Metadata-Version: 2.1
Name: mydataviewer_GUI
Version: 0.2
Summary: A Lightweight Real-Time Interactive Data Viewer for Python
Home-page: https://github.com/MohsenAskar
Author: Mohsen Askar
Author-email: ceaser198511@gmail.com
License: MIT
Classifier: Programming Language :: Python :: 3
Classifier: License :: OSI Approved :: MIT License
License-File: LICENSE.txt
Requires-Dist: pandas
Requires-Dist: pyqt5
Requires-Dist: qtconsole
Requires-Dist: ipykernel
Requires-Dist: jupyter-client
